SimpleQualtrics/SimpleQualtrics.py
SimpleQualtrics/__init__.py
test/SimpleQualtricsTest.py
test/__init__.py
SimpleQualtrics-1.0.3.dist-info/LICENSE
SimpleQualtrics-1.0.3.dist-info/METADATA
SimpleQualtrics-1.0.3.dist-info/WHEEL
SimpleQualtrics-1.0.3.dist-info/top_level.txt
SimpleQualtrics-1.0.3.dist-info/RECORD
