Metadata-Version: 2.1
Name: SimpleQualtrics
Version: 1.0.3
Summary: Python module to support Qualtrics APIs
Home-page: https://github.com/charlesweir/SimpleQualtrics
Author: Charles Weir
Author-email: pypi.cafaw@xoxy.net
License: UNKNOWN
Keywords: qualtrics API https
Platform: UNKNOWN
Classifier: Programming Language :: Python :: 3
Classifier: License :: OSI Approved :: GNU General Public License v3 (GPLv3)
Classifier: Operating System :: OS Independent
Classifier: Natural Language :: English
Classifier: Topic :: Communications
Requires-Python: >=3.7
Requires-Dist: requests (>=2.25.1)
Requires-Dist: PyYAML (>=5.3.1)
